{
  "routes": [
    {
      "method": "GET",
      "path": "/counters",
      "handler": "counter.find",
      "config": {
        "policies": []
      }
    },
    {
      "method": "GET",
      "path": "/counters/count",
      "handler": "counter.count",
      "config": {
        "policies": []
      }
    },
    {
      "method": "GET",
      "path": "/counters/:id",
      "handler": "counter.findOne",
      "config": {
        "policies": []
      }
    },
    {
      "method": "POST",
      "path": "/counters",
      "handler": "counter.create",
      "config": {
        "policies": []
      }
    },
    {
      "method": "PUT",
      "path": "/counters/:id",
      "handler": "counter.update",
      "config": {
        "policies": []
      }
    },
    {
      "method": "DELETE",
      "path": "/counters/:id",
      "handler": "counter.delete",
      "config": {
        "policies": []
      }
    }
  ]
}
